AUTHORS.rst
CONTRIBUTING.rst
HISTORY.rst
LICENSE
MANIFEST.in
README.rst
setup.cfg
setup.py
docs/Makefile
docs/authors.rst
docs/conf.py
docs/contributing.rst
docs/history.rst
docs/index.rst
docs/installation.rst
docs/make.bat
docs/readme.rst
docs/usage.rst
sample12345/__init__.py
sample12345/sample12345.py
sample12345.egg-info/PKG-INFO
sample12345.egg-info/SOURCES.txt
sample12345.egg-info/dependency_links.txt
sample12345.egg-info/not-zip-safe
sample12345.egg-info/requires.txt
sample12345.egg-info/top_level.txt
tests/__init__.py
tests/test_sample12345.py